proxysiphon/__init__.py
proxysiphon/agemodel.py
proxysiphon/lgm.py
proxysiphon/proxychimp.py
proxysiphon/records.py
proxysiphon/lmr_hdf5/__init__.py
proxysiphon/lmr_hdf5/foram_seasons.nc
proxysiphon/tests/__init__.py
proxysiphon/tests/test_proxychimp.py
proxysiphon/tests/test_records.py
proxysiphon-0.0.1a5.dist-info/LICENSE
proxysiphon-0.0.1a5.dist-info/METADATA
proxysiphon-0.0.1a5.dist-info/WHEEL
proxysiphon-0.0.1a5.dist-info/top_level.txt
proxysiphon-0.0.1a5.dist-info/RECORD
